roiextractors/__init__.py
roiextractors/core_utils.py
roiextractors/extraction_tools.py
roiextractors/extractorlist.py
roiextractors/imagingextractor.py
roiextractors/multiimagingextractor.py
roiextractors/multisegmentationextractor.py
roiextractors/segmentationextractor.py
roiextractors/testing.py
roiextractors/volumetricimagingextractor.py
roiextractors/example_datasets/__init__.py
roiextractors/example_datasets/toy_example.py
roiextractors/extractors/__init__.py
roiextractors/extractors/caiman/__init__.py
roiextractors/extractors/caiman/caimansegmentationextractor.py
roiextractors/extractors/femtonicsimagingextractor/__init__.py
roiextractors/extractors/femtonicsimagingextractor/femtonicsimagingextractor.py
roiextractors/extractors/hdf5imagingextractor/__init__.py
roiextractors/extractors/hdf5imagingextractor/hdf5imagingextractor.py
roiextractors/extractors/inscopixextractors/__init__.py
roiextractors/extractors/inscopixextractors/inscopiximagingextractor.py
roiextractors/extractors/inscopixextractors/inscopixsegmentationextractor.py
roiextractors/extractors/memmapextractors/__init__.py
roiextractors/extractors/memmapextractors/memmapextractors.py
roiextractors/extractors/memmapextractors/numpymemampextractor.py
roiextractors/extractors/minian/__init__.py
roiextractors/extractors/minian/miniansegmentationextractor.py
roiextractors/extractors/miniscopeimagingextractor/__init__.py
roiextractors/extractors/miniscopeimagingextractor/miniscope_utils.py
roiextractors/extractors/miniscopeimagingextractor/miniscopeimagingextractor.py
roiextractors/extractors/numpyextractors/__init__.py
roiextractors/extractors/numpyextractors/numpyextractors.py
roiextractors/extractors/nwbextractors/__init__.py
roiextractors/extractors/nwbextractors/nwbextractors.py
roiextractors/extractors/sbximagingextractor/__init__.py
roiextractors/extractors/sbximagingextractor/sbximagingextractor.py
roiextractors/extractors/schnitzerextractor/__init__.py
roiextractors-0.7.2.dist-info/licenses/LICENSE.txt
roiextractors-0.7.2.dist-info/METADATA
roiextractors-0.7.2.dist-info/WHEEL
roiextractors-0.7.2.dist-info/top_level.txt
roiextractors-0.7.2.dist-info/RECORD
