Metadata-Version: 2.4
Name: roiextractors
Version: 0.7.2
Summary: Python module for extracting optical physiology ROIs and traces for various file types and formats
Author: Heberto Mayorquin, Szonja Weigl, Cody Baker, Alessio Buccino, Paul Adkisson, Alessandra Trapani, Daphné de Quatrebarbes
Author-email: Ben Dichter <ben.dichter@gmail.com>
License: BSD 3-Clause License
Project-URL: Homepage, https://github.com/catalystneuro/roiextractors
Project-URL: Documentation, https://roiextractors.readthedocs.io//
Project-URL: Changelog, https://github.com/catalystneuro/roiextractors/blob/main/CHANGELOG.md
Keywords: ROI,extraction,optical physiology
Classifier: Intended Audience :: Science/Research
Classifier: Programming Language :: Python :: 3.10
Classifier: Programming Language :: Python :: 3.11
Classifier: Programming Language :: Python :: 3.12
Classifier: Operating System :: POSIX :: Linux
Classifier: Operating System :: Microsoft :: Windows
Classifier: Operating System :: MacOS
Classifier: License :: OSI Approved :: BSD License
Requires-Python: >=3.10
License-File: LICENSE.txt
Requires-Dist: h5py>=2.10.0
Requires-Dist: pynwb>=2.0.1
Requires-Dist: tqdm>=4.48.2
Requires-Dist: lazy_ops>=0.2.0
Requires-Dist: dill>=0.3.2
Requires-Dist: scipy>=1.5.2
Requires-Dist: psutil>=5.8.0
Requires-Dist: PyYAML
Requires-Dist: lxml
Requires-Dist: packaging
Requires-Dist: zarr<3,>=2
Requires-Dist: numcodecs<0.16.0
Provides-Extra: full
Requires-Dist: tifffile>=2018.11.6; extra == "full"
Requires-Dist: scanimage-tiff-reader>=1.4.1.4; extra == "full"
Requires-Dist: neuroconv[video]>=0.4.6; extra == "full"
Requires-Dist: opencv-python-headless>=4.8.1.78; extra == "full"
Requires-Dist: natsort>=8.3.1; extra == "full"
Requires-Dist: isx>=2.0; (sys_platform != "darwin" or platform_machine != "arm64") and extra == "full"
Provides-Extra: test
Requires-Dist: pytest; extra == "test"
Requires-Dist: pytest-cov; extra == "test"
Requires-Dist: parameterized==0.8.1; extra == "test"
Requires-Dist: spikeinterface>=0.100.7; extra == "test"
Requires-Dist: pytest-xdist; extra == "test"
Provides-Extra: docs
Requires-Dist: Jinja2; extra == "docs"
Requires-Dist: Sphinx; extra == "docs"
Requires-Dist: sphinx_rtd_theme; extra == "docs"
Requires-Dist: readthedocs-sphinx-search; extra == "docs"
Requires-Dist: sphinx-toggleprompt; extra == "docs"
Requires-Dist: sphinx-copybutton; extra == "docs"
Requires-Dist: pydata_sphinx_theme; extra == "docs"
Dynamic: license-file
